{
  "name" : "opengl-tests",
  "version-string" : "1.0.0",
  "builtin-baseline" : "e590c2b30c08caf1dd8d612ec602a003f9784b7d",
  "dependencies" : [ {
    "name" : "egl-registry",
    "version>=" : "2024-01-25"
  }, {
    "name" : "opengl-registry",
    "version>=" : "2024-02-10#1"
  }, {
    "name" : "opengl",
    "version>=" : "2022-12-04#3"
  }, {
    "name" : "vcpkg-cmake-config",
    "version>=" : "2024-05-23"
  }, {
    "name" : "vcpkg-cmake",
    "version>=" : "2024-04-23"
  }, {
    "name" : "glew",
    "version>=" : "2.2.0#3"
  } ]
}